tsv_data_analytics/__init__.py
tsv_data_analytics/file_io_wrapper.py
tsv_data_analytics/file_paths_data_reader.py
tsv_data_analytics/file_paths_reader.py
tsv_data_analytics/file_paths_util.py
tsv_data_analytics/funclib.py
tsv_data_analytics/s3_wrapper.py
tsv_data_analytics/tsv.py
tsv_data_analytics/tsvutils.py
tsv_data_analytics/utils.py
tsv_data_analytics-0.2.8.dist-info/METADATA
tsv_data_analytics-0.2.8.dist-info/WHEEL
tsv_data_analytics-0.2.8.dist-info/top_level.txt
tsv_data_analytics-0.2.8.dist-info/RECORD
