Metadata-Version: 2.1
Name: tsv-data-analytics
Version: 0.2.8
Summary: Utilities to work with TSV file format
Home-page: https://github.com/CrowdStrike/tsv-data-analytics
Author: amit jaiswal
Author-email: amit.jaiswal@gmail.com
License: UNKNOWN
Project-URL: Bug Tracker, https://github.com/CrowdStrike/tsv-data-analytics/browse
Platform: UNKNOWN
Classifier: Programming Language :: Python :: 3
Classifier: License :: OSI Approved :: MIT License
Classifier: Operating System :: OS Independent
Requires-Python: >=3.6
Requires-Dist: boto3
Requires-Dist: mmh3
Requires-Dist: numpy
Requires-Dist: pandas
Requires-Dist: statistics
Requires-Dist: requests
